catpointer/__init__.py
catpointer/game.py
catpointer/models.py
catpointer/assets/cat_16x16.png
pyxel_catpointer-0.1.6.dist-info/METADATA
pyxel_catpointer-0.1.6.dist-info/RECORD
pyxel_catpointer-0.1.6.dist-info/WHEEL
pyxel_catpointer-0.1.6.dist-info/entry_points.txt
pyxel_catpointer-0.1.6.dist-info/top_level.txt
